CHANGELOG.txt
LICENCE.txt
MANIFEST.in
README.txt
setup.py
maxfancyprint/__init__.py
maxfancyprint.egg-info/PKG-INFO
maxfancyprint.egg-info/SOURCES.txt
maxfancyprint.egg-info/dependency_links.txt
maxfancyprint.egg-info/top_level.txt