Metadata-Version: 2.1
Name: maxfancyprint
Version: 0.0.1
Summary: Fancy way of printing things
Home-page: UNKNOWN
Author: Max-Emil Hansen
Author-email: max8han@gmail.com
License: UNKNOWN
Keywords: print
Platform: UNKNOWN
Classifier: Development Status :: 5 - Production/Stable
Classifier: Intended Audience :: Education
Classifier: Operating System :: Microsoft :: Windows :: Windows 10
Classifier: License :: OSI Approved :: MIT License
Classifier: Programming Language :: Python :: 3
License-File: LICENCE.txt
